cellyzer_gui/gui.py
cellyzer_gui/assets/add-call.gif
cellyzer_gui/assets/add-dataset.gif
cellyzer_gui/assets/functions.gif
cellyzer_gui/assets/gui.css
cellyzer_gui-1.0.0.dist-info/LICENSE
cellyzer_gui-1.0.0.dist-info/METADATA
cellyzer_gui-1.0.0.dist-info/WHEEL
cellyzer_gui-1.0.0.dist-info/entry_points.txt
cellyzer_gui-1.0.0.dist-info/top_level.txt
cellyzer_gui-1.0.0.dist-info/RECORD
