Metadata-Version: 2.1
Name: cellyzer-gui
Version: 1.0.0
Summary: GUI for Cellyzer,a CDR(Call Data Records) data analyzing library
Home-page: https://github.com/anjuchamantha/cellyzer---CDR-data-analyzer
Author: Team Cellyzer
Author-email: chamantha97anju@gmail.com
License: MIT
Project-URL: Documentation, https://anjuchamantha.github.io/cellyzer---CDR-data-analyzer/
Project-URL: Source Code, https://github.com/anjuchamantha/cellyzer---CDR-data-analyzer
Platform: UNKNOWN
Classifier: License :: OSI Approved :: MIT License
Classifier: Intended Audience :: Science/Research
Classifier: Programming Language :: Python :: 3.7
Requires-Dist: cellyzer (>=1.1.1)
Requires-Dist: dash (==1.10.0)
Requires-Dist: dash-admin-components (==0.1.4)
Requires-Dist: dash-bootstrap-components (==0.9.2)
